lang_spider/__init__.py
lang_spider/scheduler.py
lang_spider/sync_spider.py
lang_spider/sync_spider_obj.py
lang_spider/web_http.py
lang_spider/service/common_crawl.py
LangSpider-1.2.dist-info/LICENSE
LangSpider-1.2.dist-info/METADATA
LangSpider-1.2.dist-info/WHEEL
LangSpider-1.2.dist-info/top_level.txt
LangSpider-1.2.dist-info/RECORD
