Metadata-Version: 2.1
Name: LangSpider
Version: 1.2
Summary: spider module
Home-page: https://github.com/langgithub/LangSpider
Author: yuanlang
Author-email: 15775691981@163.com
License: MIT License
Platform: UNKNOWN
Classifier: Programming Language :: Python :: 3
Classifier: License :: OSI Approved :: MIT License
Classifier: Operating System :: OS Independent
Requires-Python: >=3.6
